{
    "description": "Un vote pourrait avoir lieu au Conseil de s\u00e9curit\u00e9 d\u00e8s mercredi.",
    "body": "La  France  et les Etats-Unis sont parvenus \u00e0 un accord sur un  projet  de r\u00e9solution de l\u2019ONU qui ouvre la voie au d\u00e9ploiement d\u2019une force africaine pour  combattre  les djihadistes dans la r\u00e9gion du Sahel, ont annonc\u00e9 des diplomates mardi 20\u00a0juin. Un vote pourrait  avoir  lieu au Conseil de s\u00e9curit\u00e9 d\u00e8s mercredi sur cette r\u00e9solution qui salue le d\u00e9ploiement du G5 Sahel mais sans lui  d\u00e9livrer  un mandat de l\u2019ONU, selon ce texte. Le  Mali , la  Mauritanie , le  Niger , le  Tchad  et le  Burkina Faso , qui composent le G5 Sahel, ont accept\u00e9 en mars de  constituer  une force de 5\u00a0000\u00a0hommes, charg\u00e9e d\u2019une mission sp\u00e9ciale de contre-terrorisme dans la r\u00e9gion du Sahel. Un premier projet de r\u00e9solution, pr\u00e9sent\u00e9 il y a deux semaines par la France, proposait que le Conseil de s\u00e9curit\u00e9 autorise une telle force disposant d\u2019un mandat de l\u2019ONU pour  \u00ab\u00a0utiliser tous les moyens n\u00e9cessaires\u00a0\u00bb  afin de  \u00ab\u00a0combattre le terrorisme, le trafic de drogue et le trafic de personnes\u00a0\u00bb . Les Etats-Unis s\u2019y \u00e9taient oppos\u00e9s, estimant que le projet de r\u00e9solution manquait de pr\u00e9cision et qu\u2019une simple d\u00e9claration du Conseil pourrait  \u00eatre  suffisante. Selon  Paris , une r\u00e9solution \u00e9tait n\u00e9cessaire, conform\u00e9ment \u00e0 une demande de l\u2019 Union africaine . Le nouveau projet de r\u00e9solution  \u00ab\u00a0salue le d\u00e9ploiement\u00a0\u00bb  du G5  \u00ab\u00a0en vue de  ramener  la paix et la s\u00e9curit\u00e9 dans la r\u00e9gion du Sahel\u00a0\u00bb . Mais il n\u2019invoque pas le chapitre\u00a07 de la charte des Nations unies, qui autorise l\u2019utilisation de la force. La France a lanc\u00e9 une intervention militaire internationale d\u2019urgence en\u00a02013 pour  faire  barrage \u00e0 des groupes djihadistes, proches d\u2019 Al-Qaida , qui occupaient le nord du Mali. Les djihadistes en ont \u00e9t\u00e9 en grande partie chass\u00e9s par l\u2019op\u00e9ration \u00ab\u00a0Serval\u00a0\u00bb \u2013 depuis devenue \u00ab\u00a0Barkhane\u00a0\u00bb \u2013, qui se poursuit encore dans les pays du G5, dans la bande sah\u00e9lo-saharienne, une zone vaste comme l\u2019 Europe . Des zones enti\u00e8res \u00e9chappent au contr\u00f4le des forces maliennes, fran\u00e7aises et de l\u2019ONU, r\u00e9guli\u00e8rement vis\u00e9es par des attaques meurtri\u00e8res malgr\u00e9 la signature en mai-juin\u00a02015 d\u2019un accord de paix cens\u00e9  isoler  d\u00e9finitivement les djihadistes.",
    "title": "G5 Sahel\u00a0: Paris et Washington s\u2019accordent sur un projet de r\u00e9solution de l\u2019ONU",
    "date": "20/06/2017",
    "url": "http://www.lemonde.fr/afrique/article/2017/06/20/g5-sahel-paris-et-washington-s-accordent-sur-un-projet-de-resolution-de-l-onu_5148302_3212.html",
    "theme": "afrique",
    "newspaper": "Le Monde"
}