{
    "description": "Depuis son exil, l'ex-agent de la NSA est sans cesse sollicit\u00e9 pour commenter l'actualit\u00e9. Bien au-del\u00e0 de la surveillance de masse, son sujet de pr\u00e9dilection.",
    "author": "Olivier Tesquet",
    "title": "Sur Arte : Edward Snowden, l\u2019espion qu'on \u00e9coute",
    "newspaper": "Telerama",
    "theme": "television",
    "url": "http://television.telerama.fr/television/sur-arte-edward-snowden-l-espion-qu-on-ecoute,159047.php",
    "date": "10/06/2017",
    "body": "Son \u00e9locution est toujours parfaite. Chaque mot est soigneusement soupes\u00e9, \u00e0 la syllabe pr\u00e8s. Le vocabulaire est pr\u00e9cis, chirurgical. Le ton, calme, r\u00e9fl\u00e9chi.  Edward Snowden  le sait : quand il parle, on l'\u00e9coute. Ses amis, ses alli\u00e9s, ses visiteurs, mais aussi ses contempteurs et ses adversaires, qui r\u00eavent de le rapatrier aux Etats-Unis manu militari. Depuis pr\u00e8s de quatre ans, l'ancien sous-traitant de la NSA dispense la bonne parole depuis Moscou, o\u00f9 une situation d'urgence est devenue son quotidien. Et c'est parti pour durer, puisque les autorit\u00e9s russes ont prolong\u00e9 son permis de s\u00e9jour jusqu'en 2020. \u201cCertaines choses sont plus importantes que la s\u00e9curit\u00e9.\u201d Quand le dala\u00ef-lama d\u00e9voue sa vie \u00e0 parcourir le monde, Edward Snowden consacre la sienne \u00e0 commenter ce qui s'y passe, derri\u00e8re un ordinateur ou devant une cam\u00e9ra. Jamais un corps prisonnier n'a fait autant de mouvements. Gr\u00e2ce au \u00ab Snowbot \u00bb (une tablette juch\u00e9e sur un aspirateur g\u00e9ant), il peut m\u00eame intervenir dans une foultitude de conf\u00e9rences \u00e0 travers le monde, o\u00f9 des audiences captiv\u00e9es boivent ses paroles comme s'il s'agissait d'un \u00e9vangile d\u00e9mat\u00e9rialis\u00e9. Il a fini par s'accommoder de cette vie, lui le  \u00ab chat d'int\u00e9rieur \u00bb.  A Flore Vasseur, la documentariste fran\u00e7aise qui a organis\u00e9 sa rencontre \u00e0 Moscou avec le professeur am\u00e9ricain Larry Lessig et la d\u00e9put\u00e9e islandaise du \u00adParti pirate Birgitta J\u00f3nsd\u00f3ttir, il commence d'ailleurs par r\u00e9p\u00e9ter qu'il est  \u00ab heureux de ne pas \u00eatre en prison \u00bb.  Et rench\u00e9rit :  \u00ab Si ma priorit\u00e9 avait \u00e9t\u00e9 la s\u00e9curit\u00e9, je n'aurais jamais quitt\u00e9 la NSA. Certaines choses sont plus importantes que la s\u00e9curit\u00e9. \u00bb Snowden est devenu un point cardinal du d\u00e9bat public Des fuites qui l'ont rendu c\u00e9l\u00e8bre, on sait presque tout. Nul besoin d'y revenir par le menu. La r\u00e9alisatrice Laura Poitras \u2014 aux premi\u00e8res loges quand Snowden \u00e9tait reclus avec des journalistes du  Guardian  dans une chambre d'h\u00f4tel de Hongkong, des gigaoctets de donn\u00e9es entre les mains \u2014 en a tir\u00e9 un docu essentiel film\u00e9 comme du cin\u00e9ma-v\u00e9rit\u00e9 :  Citizenfour .  Un portrait \u00e0 hauteur d'homme, nerveux et captivant. Oliver Stone, quant \u00e0 lui, s'est charg\u00e9 de lui offrir une stature, dans un biopic,  Snowden ,  port\u00e9 par Joseph Gordon-Levitt. In\u00e9gal mais qui fait sens. En une paire d'ann\u00e9es, l'espion repenti est devenu un point cardinal du d\u00e9bat public, un symbole doubl\u00e9 d'une autorit\u00e9 morale. Un vieux sage, \u00e0 34 ans. Pr\u00e9coce. \u00c7a l'autorise \u00e0 digresser, \u00e0 sortir des sentiers balis\u00e9s de la surveillance de masse, ce th\u00e8me qu'il conna\u00eet mieux que quiconque. A l'instar de nos \u00e9ditorialistes (parfois) aga\u00e7ants, il a gagn\u00e9 le droit d'avoir un avis sur tout ou presque. Ce que dit le lanceur d'alerte est\u00a0parole d'\u00e9vangile\u00a0 Ce n'est pas un hasard si, au moment de s'interroger sur le devenir de nos d\u00e9mocraties malades, Flore Vasseur se tourne spontan\u00e9ment vers Edward Snowden. Trump vient d'\u00eatre \u00e9lu pr\u00e9sident des Etats-Unis, les soup\u00e7ons d'ing\u00e9rence russe dans la campagne pr\u00e9sidentielle am\u00e9ricaine vont bon train, et dans un monde bunkeris\u00e9, atomis\u00e9, le lanceur d'alerte est autoris\u00e9 \u00e0 parler avec les intonations de voix de ceux qui ont tutoy\u00e9 l'enfer. Ou, du moins, \u00e0 faire les cent pas dans le purgatoire (soit la zone internationale de l'a\u00e9roport de Cheremetievo). Il fait d\u00e9sormais partie d'un c\u00e9nacle de  \u00ab privil\u00e9gi\u00e9s \u00bb,  qui ont fait connaissance quasi bibliquement avec les rouages de la machine \u00e9tatique.\u00a0Quand Lessig, professeur de droit \u00e0 Harvard, candidat malheureux aux primaires d\u00e9mocrates, exil\u00e9 en Islande puis au Rwanda, s'inqui\u00e8te de voir le camp des progressistes  \u00ab dans une impasse \u00bb,  que fait-il ? Il s'en remet \u00e0 Snowden et \u00e0 sa figure sacrificielle. Il n'est pas le seul : un peu partout dans la soci\u00e9t\u00e9 civile, on sollicite son diagnostic, on esp\u00e8re des r\u00e9ponses, comme si une visite chez le docteur Snowden \u00e9tait susceptible de chasser les vilains nuages qui planent au-dessus de nos t\u00eates."
}