{
    "description": "Locaux en tr\u00e8s mauvais \u00e9tat, tensions, manque de moyens financiers\u2026 Autrefois en pointe, le\u00a0laboratoire de l\u2019agence fran\u00e7aise, \u00e0 Ch\u00e2tenay-Malabry, est s\u00e9v\u00e8rement jug\u00e9 par un rapport interne. De r\u00e9centes nominations pourraient toutefois le relancer.",
    "author": "Pierre Carrey, Sylvain Mouillard, Luca  Endrizzi",
    "title": "L\u2019antidopage fran\u00e7ais se fait du\u00a0mauvais sang",
    "newspaper": "Liberation",
    "theme": "sports",
    "url": "http://www.liberation.fr/sports/2017/06/12/l-antidopage-francais-se-fait-du-mauvais-sang_1576351?xtor=rss-450",
    "date": "12/06/2017",
    "body": "La lutte antidopage fran\u00e7aise, longtemps consid\u00e9r\u00e9e comme la plus efficace du monde, est-elle tomb\u00e9e en miettes ? Voil\u00e0 un \u00e9pineux dossier pour la nouvelle ministre des Sports, l\u2019ancienne escrimeuse Laura Flessel, \u00e0 l\u2019heure o\u00f9 Paris m\u00e8ne une candidature pour les Jeux olympiques de\u00a02024 plac\u00e9e sous le sceau de la cr\u00e9dibilit\u00e9. Val\u00e9rie Fourneyron (\u00e9galement ministre des Sports de\u00a02012\u00a0\u00e0\u00a02014), aujourd\u2019hui pr\u00e9sidente du comit\u00e9 m\u00e9dical de l\u2019Agence mondiale antidopage (AMA), a son avis sur la question :  \u00abL\u2019Agence fran\u00e7aise de lutte contre le dopage  [AFLD]  et son laboratoire    ne font plus partie de ce r\u00e9seau de r\u00e9f\u00e9rence. Or, dans ce domaine, ce sont d\u2019abord les labos qui comptent.\u00bb M\u00eame le nouveau directeur de l\u2019\u00e9tablissement de Ch\u00e2tenay-Malabry, (Hauts-de-Seine), Michel Audran, admet cette perte de vitesse :  \u00abC\u2019est le labo de Cologne qui est devenu pr\u00e9pond\u00e9rant.\u00bb Il semble loin le temps o\u00f9 la France \u00e9tait le leader mondial dans la lutte contre la fraude sportive. En\u00a02000, l\u2019\u00e9quipe de Ch\u00e2tenay-Malabry pouvait se targuer d\u2019avoir d\u00e9velopp\u00e9 le\u00a0test de d\u00e9tection de l\u2019EPO. En\u00a02008, elle \u00e9tait encore en\u00a0premi\u00e8re ligne pour avoir fait tomber plusieurs concurrents hupp\u00e9s du\u00a0Tour de France, contr\u00f4l\u00e9s positifs \u00e0 la Cera, une forme d\u2019EPO. Aujourd\u2019hui, les locaux seraient dans un \u00e9tat de d\u00e9labrement inqui\u00e9tant, \u00e0 en croire un rapport command\u00e9 par le\u00a0comit\u00e9 d\u2019hygi\u00e8ne, de s\u00e9curit\u00e9 et des conditions de\u00a0travail de l\u2019AFLD, r\u00e9sultat d\u2019une enqu\u00eate interne men\u00e9e en\u00a02015 et\u00a02016, que  Lib\u00e9ration  a pu consulter. Malaise social Les\u00a050\u00a0pages compil\u00e9es par la soci\u00e9t\u00e9 El\u00e9as d\u00e9crivent un management d\u00e9faillant ainsi qu\u2019un manque de moyens, qui se traduit notamment par la  \u00abv\u00e9tust\u00e9\u00bb  du laboratoire.  \u00abLes locaux sont anciens et connaissent quelques faiblesses structurelles (fuites d\u2019eau,\u00a0etc.), les bureaux sont exigus et leur respect des normes de s\u00e9curit\u00e9 serait \u00e0 v\u00e9rifier\u00bb , d\u00e9taille le rapport. Une salari\u00e9e anonyme est cit\u00e9e dans le document :  \u00abMon Dieu, ce n\u2019est pas un labo ! Tout tombe en ruine\u2026 J\u2019ai honte.\u00bb  Autre difficult\u00e9 de l\u2019antidopage fran\u00e7ais, qui pourrait menacer son efficacit\u00e9, le malaise social qui s\u00e9vissait en\u00a02015 et\u00a02016. Le rapport d\u2019audit rel\u00e8ve  \u00abla perte de rep\u00e8res\u00bb des salari\u00e9s, \u00abl\u2019in\u00e9galit\u00e9 de traitement qui favorise les ambiances de\u00a0travail d\u00e9l\u00e9t\u00e8res, voire conflictuelles\u00bb .  \u00abIl est \u00e9loquent, par exemple, que tous les\u00a0salari\u00e9s de cette petite institution [une soixantaine de personnes, ndlr] ne se connaissent pas forc\u00e9ment, notamment les\u00a0salari\u00e9s de Ch\u00e2tenay-Malabry et\u00a0ceux de Paris  [install\u00e9s \u00e0 22 kilom\u00e8tres].\u00bb Plus grave, toujours selon le rapport d\u2019audit, l\u2019Agence mondiale antidopage enverrait au laboratoire fran\u00e7ais cinq\u00a0\u00e9chantillons surprises \u00e0 analyser chaque ann\u00e9e, alors que cette \u00e9valuation  \u00abs\u2019appuyait sur un\u00a0seul test annuel auparavant\u00bb . Une preuve que l\u2019institution internationale douterait de la fiabilit\u00e9 de\u00a0Ch\u00e2tenay-Malabry ? Antoine Coquerel, directeur en poste jusqu\u2019en novembre\u00a02016, d\u00e9ment formellement aupr\u00e8s de  Lib\u00e9ration  que l\u2019AMA ait augment\u00e9 ses contr\u00f4les de v\u00e9rification. L\u2019agence mondiale n\u2019a en tout cas jamais suspendu le laboratoire fran\u00e7ais \u00e0 titre provisoire, comme elle le fait volontiers en cas de doute. Du c\u00f4t\u00e9 de l\u2019AFLD, on tient \u00e0 minimiser le contenu du rapport, consid\u00e9r\u00e9 comme  \u00abdat\u00e9\u00bb -  contrairement \u00e0 Guy Coisy, repr\u00e9sentant national de la CGT\u00a0Sport, qui affirme que  \u00abrien n\u2019a vraiment chang\u00e9\u00bb.  L\u2019agence reconna\u00eet cependant que l\u2019\u00e9tablissement de Ch\u00e2tenay, localis\u00e9 dans un\u00a0ancien gymnase,  \u00abn\u2019est pas dans un bon \u00e9tat mobilier\u00bb  et que de co\u00fbteux investissements en mat\u00e9riel sont n\u00e9cessaires. D\u2019autant que le cahier des charges de l\u2019AMA se r\u00e9v\u00e8le de plus en\u00a0plus exigeant et pointu. L\u2019AFLD estime par ailleurs que ses probl\u00e8mes de management ont \u00e9t\u00e9  \u00abassainis\u00bb  et que ses  \u00abcadres ont \u00e9t\u00e9 renouvel\u00e9s\u00bb  ou devraient l\u2019\u00eatre sous peu.Ainsi, la plus haute autorit\u00e9 de l\u2019agence, le pr\u00e9sident Bruno Genevois, prendra sa retraite cet \u00e9t\u00e9, \u00e0 l\u2019\u00e2ge de\u00a075\u00a0ans. Ce conseiller d\u2019Etat avait cristallis\u00e9 les critiques il y a un an, apparaissant d\u00e9muni dans un num\u00e9ro de  Cash Investigation  sur France\u00a02, o\u00f9 il ne semblait pas trouver de r\u00e9ponse sur le traitement de\u00a0l\u2019affaire du \u00abdocteur Mabuse\u00bb, un\u00a0naturopathe soup\u00e7onn\u00e9 de doper diff\u00e9rents athl\u00e8tes. Fantasme Ces changements de personnes pourraient aider l\u2019AFLD \u00e0 restaurer sa r\u00e9putation, comme en atteste aussi le recrutement en d\u00e9cembre du tr\u00e8s respect\u00e9 Michel Audran, 68\u00a0ans, ancien professeur de biophysique \u00e0 l\u2019universit\u00e9 de Montpellier et depuis f\u00e9vrier aux commandes de Ch\u00e2tenay-Malabry.  \u00abLe laboratoire semble sortir d\u2019une p\u00e9riode tr\u00e8s difficile o\u00f9 il avait perdu du terrain par rapport \u00e0 ses concurrents,  juge Val\u00e9rie Fourneyron.  L\u2019AFLD n\u2019avait pas de position scientifique ni manag\u00e9riale. Combien de\u00a0fois ai-je regrett\u00e9 qu\u2019elle n\u2019envoie personne aux colloques internationaux, qu\u2019elle ne candidate pas aux\u00a0appels \u00e0 projets de l\u2019AMA, qui sont aussi une fa\u00e7on de diversifier ses ressources ? Apr\u00e8s ces difficult\u00e9s de gouvernance, l\u2019arriv\u00e9e d\u2019Audran me rassure.\u00bb Au-del\u00e0 de ces d\u00e9bats internes, l\u2019ancien journaliste de  l\u2019Equipe  Damien Ressiot, d\u00e9sormais en charge des contr\u00f4les \u00e0 l\u2019AFLD, nuance l\u2019id\u00e9e d\u2019un antidopage fran\u00e7ais en perte de vitesse. Il conteste le fantasme d\u2019un  \u00ab\u00e2ge d\u2019or\u00bb,  celui des ann\u00e9es\u00a02000, lorsque l\u2019ancien pr\u00e9sident de l\u2019agence Pierre Bordry sonnait la charge sans m\u00e9nagement contre Lance Armstrong et les tricheurs du\u00a0peloton cycliste.  \u00abJe fais le tri entre la r\u00e9elle influence et ce qui relevait davantage de la gesticulation, notamment dans un contexte\u00a0d\u2019actualit\u00e9 tr\u00e8s porteuse\u00bb,  dit-il .  Pour Damien Ressiot, l\u2019AFLD s\u2019est\u00a0 \u00abconsid\u00e9rablement r\u00e9veill\u00e9e depuis un an\u00bb.  Et m\u00eame si\u00a0Ch\u00e2tenay-Malabry n\u2019est\u00a0pas adoss\u00e9 \u00e0 une universit\u00e9, comme c\u2019est le cas\u00a0\u00e0 Cologne (200\u00a0chercheurs travaillent sur le sujet en Allemagne, z\u00e9ro en France), le directeur des contr\u00f4les estime que le labo  \u00abse trouve parmi les dix, douze qui comptent au niveau mondial\u00bb. Rien \u00e0 voir, donc, avec une ruine totale. La France n\u2019est ni la Russie (accus\u00e9e d\u2019avoir mis en place un dopage d\u2019Etat et organis\u00e9 la destruction de plusieurs \u00e9chantillons suspects avec l\u2019aide des services secrets lors des JO de Sotchi en\u00a02014) ni le Br\u00e9sil (le pays h\u00f4te des Jeux\u00a02016 pr\u00e9sentait des failles de s\u00e9curit\u00e9 dans l\u2019acc\u00e8s \u00e0 son laboratoire, qui avait ainsi \u00e9t\u00e9 suspendu plusieurs mois par l\u2019AMA). Autre difficult\u00e9, l\u2019\u00e9volution de la triche sportive, avec des athl\u00e8tes qui ont diminu\u00e9 les doses de produits lourds, compliquant les contr\u00f4les et, de fait, les coups m\u00e9diatiques. Damien Ressiot :  \u00abLes tricheurs sont r\u00e9actifs, sans cesse \u00e0 la limite. Avec les microdoses, les fen\u00eatres de d\u00e9tection sont de plus en plus r\u00e9duites. Les sportifs parviennent \u00e0 lisser leurs param\u00e8tres pour \u00eatre borderline, mais pas dans le rouge absolu. Plus que jamais, en mati\u00e8re de lutte antidopage, tout est gris.\u00bb Reste que l\u2019Agence fran\u00e7aise, en pleine reconqu\u00eate de s\u00e9r\u00e9nit\u00e9 et\u00a0d\u2019image, peine financi\u00e8rement.  \u00abCela fait plusieurs ann\u00e9es que nos\u00a0d\u00e9penses sont sup\u00e9rieures \u00e0 nos\u00a0recettes\u00bb,  explique-t-elle. Jusqu\u2019en\u00a02016, les dotations \u00e9tatiques \u00e9taient stables : 7,8\u00a0millions d\u2019euros par an. Mais en raison du gel des\u00a0cr\u00e9dits, seule une partie \u00e9tait vers\u00e9e, soit\u00a07,4\u00a0millions d\u2019euros. Cette ann\u00e9e, l\u2019Etat a d\u00e9cid\u00e9 d\u2019augmenter sa participation, \u00e0 hauteur de\u00a08,5\u00a0millions. Mais l\u00e0\u00a0encore, Bercy a bloqu\u00e9 une partie de la somme. R\u00e9sultat, l\u2019agence ne\u00a0touchera cette ann\u00e9e que 7,8\u00a0millions. Insuffisant pour \u00e9quilibrer les\u00a0comptes, en d\u00e9ficit de\u00a0600 000\u00a0euros en moyenne tous\u00a0les ans. Certes, l\u2019AFLD a d\u00e9velopp\u00e9 ses ressources ext\u00e9rieures, notamment les analyses r\u00e9alis\u00e9es pour des agences gouvernementales ou f\u00e9d\u00e9rations tierces, en Argentine, Ethiopie, Kenya, par exemple. Ces revenus ont progress\u00e9 de\u00a056 % en\u00a02016, portant le chiffre d\u2019affaires de cette activit\u00e9 de\u00a01\u00a0million \u00e0 1,5\u00a0million d\u2019euros. Mais cette augmentation pourrait n\u2019\u00eatre que conjoncturelle, li\u00e9e notamment \u00e0 la fermeture ou\u00a0\u00e0 la suspension de 20 % des laboratoires antidopage \u00e0 travers le monde. \u00abChoses catastrophiques\u00bb Pour faire face aux indispensables investissements pour maintenir aux normes la structure de Ch\u00e2tenay-Malabry, ce sont donc les contr\u00f4les qui servent de  \u00abvariable d\u2019ajustement\u00bb . En\u00a02010, l\u2019AFLD a effectu\u00e9\u00a09 800\u00a0pr\u00e9l\u00e8vements sur des athl\u00e8tes. Elle en a r\u00e9alis\u00e9 8 600 en\u00a02016, selon le rapport d\u2019activit\u00e9 qui sera d\u00e9voil\u00e9 ce mardi \u00e0 Paris. L\u2019\u00e9rosion devrait se poursuivre en\u00a02017 et le nombre de tests passer sous la barre des\u00a08 000, ce qui reviendrait \u00e0 une baisse de quasiment\u00a020 % en sept\u00a0ans. Le d\u00e9clin des contr\u00f4les pourrait toucher en premier lieu le sport amateur.  \u00abC\u2019est risqu\u00e9, car nos r\u00e9sultats dans ce domaine sont effarants, pointe Ressiot. D\u00e8s qu\u2019on va mettre notre nez dans les sports \u00e9mergents, notamment de combat, on tombe sur des choses catastrophiques, avec des produits lourds, comme les st\u00e9ro\u00efdes. Il faudrait augmenter les contr\u00f4les, cela fait partie de notre mission de\u00a0sant\u00e9 publique.\u00bb  En attendant le r\u00e9sultat de l\u2019attribution de l\u2019organisation des Jeux de\u00a02024, qui pourrait donner un coup de fouet \u00e9conomique tr\u00e8s attendu \u00e0 l\u2019AFLD, l\u2019institution r\u00e9fl\u00e9chit \u00e0 d\u00e9velopper d\u2019autres sources de revenus. L\u2019id\u00e9e de r\u00e9server \u00e0 l\u2019AFLD une partie de la \u00abtaxe Buffet\u00bb sur les droits t\u00e9l\u00e9vis\u00e9s du sport professionnel refait surface r\u00e9guli\u00e8rement. De nouveau \u00e9voqu\u00e9e \u00e0 l\u2019Assembl\u00e9e nationale en novembre\u00a02016, elle a finalement \u00e9t\u00e9 abandonn\u00e9e."
}