{
    "description": "INTERVIEW - Cet \u00e9diteur vient de lancer \u00ab\u00a0Le voyageur affam\u00e9\u00a0\u00bb, une ing\u00e9nieuse collection de guides touristiques et gastronomiques.",
    "author": "Colette Monsat",
    "title": "Laurent S\u00e9minel: \u00abLa d\u00e9couverte d'une ville passe par la nourriture\u00bb",
    "date": "24/06/2017",
    "theme": "gastronomie",
    "newspaper": "Le Figaro",
    "url": "http://www.lefigaro.fr/gastronomie/2017/06/24/30005-20170624ARTFIG00014-laurent-seminel-la-decouverte-d-une-ville-passe-par-la-nourriture.php",
    "body": "Menu Fretin est une maison d'\u00e9dition qui ne ressemble \u00e0 aucune autre. Son fondateur, Laurent S\u00e9minel, publie des \u00ablivres de gastronomie qui s'adressent plus au cerveau qu'\u00e0 l'estomac\u00bb, persuad\u00e9 que la cuisine est avant tout un fait culturel qui d\u00e9passe largement le simple instinct de se nourrir pour assurer sa survie. Pas \u00e9tonnant donc que sa nouvelle collection de guides,  \u00abLe voyageur affam\u00e9\u00bb , s'apparente \u00e0 un ovni dans le monde assez format\u00e9 de l'\u00e9dition gourmande. Ces astucieux viatiques, v\u00e9ritables poids plumes adapt\u00e9s \u00e0 l'\u00e8re des voyages low-costs, sont con\u00e7us comme de petits origamis touristiques. Leurs plis rec\u00e8lent une carte de la ville avec les principaux lieux d'int\u00e9r\u00eat culturel et, pour chacun, les meilleurs spots pour manger, boire un verre ou acheter des produits locaux, aux abords imm\u00e9diats. Soit une trentaine d'adresses, tri\u00e9es sur le volet, qui participent de la compr\u00e9hension d'une grande ville. Apr\u00e8s J\u00e9rusalem et Bruxelles, deux guides tout frais viennent nourrir les voyages: Londres et Kyoto. Le FIGARO. - Quel est le concept de ces nouveaux guides? Laurent S\u00e9minel. -  Il correspond d'abord \u00e0 un aspect pratique en partant du principe que, dans une ville, quelle qu'elle soit, on aura besoin de manger, souvent au restaurant. Habituellement, on note dans un guide une adresse qui a l'air bien et puis finalement, c'est la visite de mus\u00e9es, de monuments qui va d\u00e9cider de notre programme. En fait, on n'est jamais au bon endroit. \u00c0 midi et demi, le restaurant rep\u00e9r\u00e9 se trouve \u00e0 l'autre bout de la ville! L'autre aspect, tr\u00e8s important, est la gastronomie comme \u00e9l\u00e9ment d\u00e9terminant de la culture de chaque personne. Pour appr\u00e9hender une ville et ses habitants, il est important de comprendre comment ils mangent. C'est particuli\u00e8rement vrai pour une ville comme Kyoto, par exemple, o\u00f9 la fa\u00e7on de manger est tr\u00e8s particuli\u00e8re, o\u00f9 un \u00e9tranger, et m\u00eame un Kyoto\u00efte, aura du mal \u00e0 trouver le mode d'emploi d'un restaurant parce qu'il n'y a ni menu ni prix\u2026 Donc il faut un d\u00e9codeur pour comprendre. \u00c0 Londres, si je veux comprendre un Anglais, j'ai besoin de savoir o\u00f9 je vais manger de la nourriture v\u00e9ritablement British. La d\u00e9couverte de la culture de l'autre passe par les mus\u00e9es, les monuments et la nourriture. Ces deux aspects sont r\u00e9unis dans nos guides. \n                                 \n                                     \u00abEn mangeant, vous allez d\u00e9couvrir la ville aussi bien qu'en marchant dans les rues ou en visitant un monument\u00bb         Laurent S\u00e9minel, \u00e9diteur     \n                             N'existe-t-il pas des voyageurs exclusivement int\u00e9ress\u00e9s par la gastronomie et non par la culture?  Si, parce qu'aujourd'hui c'est plus facile et pas forc\u00e9ment plus cher d'aller \u00e0 Londres, Bruxelles, Amsterdam, en train ou en avion, que dans certaines villes de l'Hexagone. C'est aussi ce public que nous visons d'une certaine mani\u00e8re, des personnes qui aiment bien manger. Notre propos consiste \u00e0 dire: \u00abEn mangeant, vous allez d\u00e9couvrir la ville aussi bien qu'en marchant dans les rues ou en visitant un monument.\u00bb Si on mange comme un Bruxellois, on va comprendre Bruxelles. La mani\u00e8re dont on se nourrit est extr\u00eamement identitaire. Et c'est l'occasion de rencontrer les habitants de ces villes. Les choses s'entrem\u00ealent. On comprend beaucoup de choses \u00e0 travers la nourriture. Par exemple, la s\u00e9paration entre l'Est et l'Ouest, \u00e0 J\u00e9rusalem. Quel public visez-vous? Un public de gens curieux, qui partent en week-end, les city breakers comme on les appelle. L'id\u00e9e est de faire des guides \u00e0 la fois pour des villes o\u00f9 il en existe d\u00e9j\u00e0 beaucoup, comme Londres ou Bruxelles, et pour celles o\u00f9 il y en a tr\u00e8s peu, comme Kyoto ou J\u00e9rusalem. Pour chaque opus, la structure est identique: une page consacr\u00e9e \u00e0 la description globale de la ville et sa fa\u00e7on de manger, les plats vraiment typiques. Puis nos quatre petits modules fa\u00e7on magazine, qui varient selon les destinations: un portrait \u00e0 Bruxelles, un mode d'emploi pour Kyoto, un article sur l'histoire des cabmen's shelter, ces petites cabines pour les taxis ou encore la mode du gin \u00e0 Londres. Nous nous positionnons comme un second guide, celui qu'on a dans sa poche pour trouver des adresses gourmandes de qualit\u00e9, le premier \u00e9tant plus classique et culturel sur la visite des monuments. \n                                 \n                                     Des livres de gastronomie qui s'adressent plus au cerveau qu'\u00e0 l'estomac     \n                             On peut vous objecter que ce sont des adresses \u00e0 la mode, appel\u00e9es \u00e0 devenir rapidement obsol\u00e8tes. Non, nous avons aussi int\u00e9gr\u00e9 des adresses tr\u00e8s anciennes dans nos guides, parce que ce sont des classiques. \u00c0 chaque fois, nous essayons de trouver le bon mix entre les institutions et les lieux \u00e0 la mode. Mais aussi d'avoir une bonne r\u00e9partition g\u00e9ographique. Quelles seront les prochaines villes de cette collection? Nous allons sortir Paris en septembre. En fran\u00e7ais et en anglais, car il y a un fort potentiel de touristes anglophones \u00e0 Paris. Les suivants seront pour 2018, parce que c'est assez long \u00e0 mettre au point. Nous ferons majoritairement des villes europ\u00e9ennes et puis d'autres, hors de l'Europe, m\u00eame si cela correspond un peu moins \u00e0 notre cible car plus \u00e9loign\u00e9es, mais o\u00f9 il se passe des choses int\u00e9ressantes. Comme le guide de Kyoto qu'on peut aussi lire sans aller l\u00e0-bas parce qu'il nous apprend beaucoup sur cette destination.  Guides \u00abLe voyageur affam\u00e9\u00bb aux  \u00c9ditions Menu Fretin . 9,50\u00a0euros. D\u00e9j\u00e0 parus: J\u00e9rusalem, Bruxelles, Kyoto, Londres. \u00c0 para\u00eetre: Paris, septembre\u00a02017. www.menufretin.fr"
}