{
    "date": "15/06/2017",
    "url": "http://bourse.lefigaro.fr/indices-actions/actu-conseils/un-pari-speculatif-sur-crossject-une-pepite-cotees-sur-alternext-6069727",
    "newspaper": "Le Figaro",
    "theme": "indices actions",
    "body": "Crossject sp\u00e9cialis\u00e9 dans les syst\u00e8mes d\u2019injection m\u00e9dicale \u00e0 usage unique, pr\u00e9-rempli, sans aiguille et automatique, est un des acteurs du march\u00e9 les plus avanc\u00e9s au monde. Le titre introduit en Bourse en f\u00e9vrier 2014 \u00e0 8,38 euros n\u2019a jusqu\u2019\u00e0 pr\u00e9sent pas vraiment convaincu.  \n Les craintes des investisseurs sur le creusement des pertes se sont confirm\u00e9es en 2016, avec un d\u00e9ficit de 6,7 millions d\u2019euros, contre 5,7 millions en 2015. La soci\u00e9t\u00e9 a expliqu\u00e9 avoir proc\u00e9d\u00e9 \u00e0 des d\u00e9veloppements importants, dont une augmentation des effectifs de 70%. Pour renforcer la tr\u00e9sorerie, Crossject a proc\u00e9d\u00e9 en avril 2017 \u00e0 une augmentation de capital ayant apport\u00e9 un produit brut de 4,98 millions d\u2019euros, lui permettant de faire face \u00e0 plus de 2 ans de consommation de cash. La soci\u00e9t\u00e9 dispose aussi de plusieurs lignes de cr\u00e9dit disponibles n\u00e9goci\u00e9es avec ses banquiers. \n Dans une \u00e9tude r\u00e9cente,  les analystes d\u2019Invest Securities sont pass\u00e9s \u00e0 \u00abl\u2019achat\u00bb sur Crossject et r\u00e9vis\u00e9 \u00e0 la hausse son objectif de cours de 8,3 \u00e0 10 euros.  Le broker appr\u00e9cie le changement de strat\u00e9gie au profit des indications d\u2019urgence permettant d\u2019acc\u00e9l\u00e9rer le processus d\u2019approbation sur le march\u00e9 am\u00e9ricain ainsi que les chances de signer des accords de licence rapidement. \n Ils estiment que le groupe a d\u00e9montr\u00e9 cliniquement l\u2019utilit\u00e9 de Zeneo par rapport aux stylos injecteurs classiques, les march\u00e9s cibl\u00e9s souffrent d\u2019un manque d\u2019innovation, l\u2019outil de production devrait bient\u00f4t \u00eatre op\u00e9rationnel et le newsflow \u00e0 court terme pourrait d\u00e9clencher une revalorisation significative du cours, souligne le bureau d\u2019\u00e9tudes. \n La soci\u00e9t\u00e9 restera en perte cette ann\u00e9e et en 2018 dans des proportions tr\u00e8s diminu\u00e9es. L\u2019\u00e9quilibre para\u00eet envisageable \u00e0 l\u2019horizon 2019. \n Notr recommandation sur  CROSSJECT: ACHAT SPECULATIF \n Le Zeneo, le produit phare de la soci\u00e9t\u00e9 repose sur un dispositif ultra-innovant, qui peut \u00eatre utilis\u00e9 pour des injections intradermiques, sous cutan\u00e9es, et intramusculaires. Il a \u00e9t\u00e9 con\u00e7u pour l\u2019auto-administration et s\u2019adapte \u00e0 la fois aux petites mol\u00e9cules, aux prot\u00e9ines comme les anticorps monoclonaux, et aux vaccins pour des volumes compris entre 0,1 et 0,6 ml. Ce dispositif est plus s\u00fbr et plus facile \u00e0 utiliser que les autres injecteurs automatiques \u00e0 aiguille actuellement commercialis\u00e9s. Il pr\u00e9sente l\u2019avantage d\u2019\u00e9liminer la plupart des facteurs de risques humains (blessures, phobie de l\u2019aiguille, etc...). L\u2019administration s\u2019effectue en une seule \u00e9tape en un dixi\u00e8me de seconde. Le Zeneo b\u00e9n\u00e9ficie d\u2019une propri\u00e9t\u00e9 intellectuelle solide jusqu\u2019en 2035 \u00e0 travers 31 familles de brevets (plus de 400 brevets).Son potentiel de d\u00e9veloppement est important. Depuis le d\u00e9but de l\u2019ann\u00e9e le titre a d\u00e9j\u00e0 regagn\u00e9 30%. Son redressement en direction du prix d\u2019introduction en Bourse au d\u00e9but de 2014 reste un objectif raisonnable. \n Cours \u00e0 date du conseil:  5,80 \u20ac \n Objectif de cours:  8,30 \u20ac soit un potentiel de +43% \n Profil d\u2019investisseur:  sp\u00e9culateur \n Horizon d\u2019investissement:  12 \u00e0 18 mois \n \n  \n      \n  \n   \n     \n\n \n \n   \n     \n\n       \n               \n           \n         \n      \n       \n               Roland Laskine \n      \n       \n       \n                           272 abonn\u00e9s \n                 \n                    \n       \n               \n           Redacteur en chef du Figaro Bourse          \n           \n           \n         Ses derniers articles \n         \n                         Europcar poursuit ses acquisitions et pr\u00e9pare une augmentation de capital \n                         Objectif de cours atteint: prise partielle de b\u00e9n\u00e9fices sur Vexim \n                         Salon du Bourget: les groupes a\u00e9ronautiques fran\u00e7ais en pleine forme \n                   \n       \n       \n \n    \n\n  \n   \n  \n      \n  \n   \n    \n \n   S'abonner au Figaro Bourse \n \n   \n\n  \n  ",
    "title": "Un pari sp\u00e9culatif sur Crossject, une p\u00e9pite cot\u00e9e sur Alternext - Indices & Actions - Le Figaro Bourse"
}