{
    "date": "16/06/2017",
    "author": "Baptiste Savignac",
    "url": "http://www.lefigaro.fr/musique/2017/06/16/03006-20170616ARTFIG00162-liam-gallagher-invite-des-fans-sans-billet-a-son-concert.php",
    "newspaper": "Le Figaro",
    "theme": "musique",
    "title": "Liam Gallagher invite des fans sans billet \u00e0 son concert",
    "description": "VID\u00c9O",
    "body": "Fr\u00e8res ennemis, les Gallagher se sont \u00e0 nouveau affront\u00e9s. Pas de violences physiques, ni d'insultes balanc\u00e9es \u00e0 la presse pour cette fois mais par une lutte acharn\u00e9e pour \u00eatre officiellement le musicien le plus g\u00e9n\u00e9reux avec ses fans. Les deux anciens membres du groupe Oasis sont d\u00e9cid\u00e9ment surprenants. Alors que l'a\u00een\u00e9, Noel, a invit\u00e9 \u00e0 son prochain concert au stade de France,  le musicien de la Garde r\u00e9publicaine Jean-Michel Mekil ayant fait vibrer le Stade de France,   avec sa reprise d'Oasis mardi soir, le cadet, Liam, a convi\u00e9 des fans rencontr\u00e9s par hasard dans les rues de Dublin \u00e0 venir \u00e0 son concert \u00e0 l'Olympia Theatre, sans ticket. Les jeunes irlandais n'avaient pas pu obtenir de place. Le concert annonc\u00e9 complet le sera donc un peu plus.  Interpell\u00e9 depuis sa voiture alors qu'il arpentait les rues de Dublin, Liam Gallagher s'est arr\u00eat\u00e9 pour signer les autographes de ces jeunes admirateurs. Adul\u00e9 par les Britanniques, le chanteur a m\u00eame pos\u00e9 pour une s\u00e9ance photo impromptue. Guitare sign\u00e9e, photo de leur chanteur pr\u00e9f\u00e9r\u00e9e en poche, les jeunes aux yeux plein d'\u00e9toiles ont eu droit \u00e0 un cadeau suppl\u00e9mentaire. Un joli coup de pub pour l'artiste plut\u00f4t habitu\u00e9 des d\u00e9rapages avec ses fans Alors qu'il \u00e9tait sur le point de repartir, un des adolescents fait part de son d\u00e9sarroi de ne pas avoir de tickets pour le concert du soir. \u00abQui a des places?\u00bb demande alors Liam Gallagher. Tous r\u00e9pondent par la n\u00e9gative. Le chanteur leur demande alors de noter leurs noms sur une feuille pour pouvoir les ajouter \u00e0 la liste des invit\u00e9s.  Partag\u00e9e hier sur sa page Facebook, la vid\u00e9o est un joli coup de pub pour l'artiste plut\u00f4t habitu\u00e9 des d\u00e9rapages avec ses fans. Le dernier en date:  ses propos homophobes \u00e0 l'\u00e9gard des supporters russes  lors de l'Euro de football l'\u00e9t\u00e9 dernier en France. Autre geste \u00e9mouvant de la part de Liam, sa performance lors du concert \u00e0 Manchester pour les victimes des attentats.  Il semble loin le temps o\u00f9 les deux fr\u00e8res Gallagher se battaient en studio, s'interrompaient en plein milieu d'un concert. Ce renouveau empreint de g\u00e9n\u00e9rosit\u00e9 laisse esp\u00e9rer les r\u00eaveurs que la reformation du groupe de rock mancunien peut \u00eatre un jour possible. "
}