{
    "description": "C\u00e9der sa maison de famille tout en \u00e9vitant les d\u00e9saccords, c\u2019est possible. Pour cela, quelques r\u00e8gles sont \u00e0 respecter. Toutes nos explications avec ",
    "author": "Caroline Mazodier",
    "title": "Comment racheter la maison familiale \u00e0 ses fr\u00e8res et s\u0153urs\u00a0?",
    "newspaper": "Le Figaro",
    "theme": "article",
    "url": "http://immobilier.lefigaro.fr/article/comment-racheter-la-maison-familiale-a-ses-freres-et-soeurs-_3bf4eb84-4d1f-11e7-83bf-99858466ff78/",
    "date": "09/06/17",
    "body": "\n \n   \n  \n  \n \n              Lorsqu\u2019une personne d\u00e9c\u00e8de en laissant une propri\u00e9t\u00e9 (maison, terrain, bois\u2026) \u00e0 ses enfants, ceux-ci en deviennent propri\u00e9taires en indivision. Chaque enfant d\u00e9tient, sur cette propri\u00e9t\u00e9, une part proportionnelle \u00e0 ses droits dans l\u2019h\u00e9ritage, et toutes les d\u00e9cisions concernant ce bien sont prises par l\u2019ensemble des h\u00e9ritiers. Il est toutefois possible de sortir de l\u2019 indivision  en attribuant d\u00e9finitivement la propri\u00e9t\u00e9 d\u2019un bien \u00e0 un indivisaire. Mais il faut pour cela proc\u00e9der \u00e0 un \u00abpartage\u00bb devant le notaire. Quelle est la diff\u00e9rence entre ce partage et une vente immobili\u00e8re? Ce  partage notari\u00e9  est tr\u00e8s diff\u00e9rent d\u2019un acte de vente: il n\u2019y a pas de diagnostic technique \u00e0 r\u00e9aliser, ni d\u2019avant-contrat \u00e0 signer, il n\u2019y a pas de droit de pr\u00e9emption au profit de la mairie, ni de droit de r\u00e9tractation pour celui qui souhaite se voir attribuer le bien. Ce dernier ne disposera d\u2019ailleurs, apr\u00e8s le partage, ni de la garantie des vices cach\u00e9s, ni de la garantie d\u2019\u00e9viction qui prot\u00e8ge d\u2019ordinaire l\u2019acqu\u00e9reur lorsque, apr\u00e8s la vente, quelqu\u2019un (occupant, voisin) revendique un droit quelconque sur le bien. Si, en revanche, le bien est vendu \u00e0 un tiers, l\u2019op\u00e9ration est soumise aux r\u00e8gles classiques de la  vente immobili\u00e8re . Notez que, lors de la vente ou du partage d\u2019un bien indivis, les h\u00e9ritiers qui occupent le logement \u00e0 titre de r\u00e9sidence principale b\u00e9n\u00e9ficient d\u2019un droit pr\u00e9f\u00e9rentiel sur ce bien: ils sont prioritaires pour le racheter. Et en cas de pluralit\u00e9 d\u2019occupants, c\u2019est le conjoint survivant qui a la priorit\u00e9. Il a, par ailleurs, le droit d\u2019occuper le logement gratuitement pendant un an. \u00bb  Comment s\u2019organiser pour conserver une maison de famille?     En tout \u00e9tat de cause, si vous envisagez un partage, ne br\u00fblez pas les \u00e9tapes: demandez d\u2019abord l\u2019accord de principe, oral ou \u00e9crit, de vos fr\u00e8res et s\u0153urs sur l\u2019op\u00e9ration de partage. Vous pourrez ensuite d\u00e9terminer ensemble le prix du bien.  Comment \u00e9valuer le prix des parts? L\u2019estimation du prix du bien peut \u00eatre r\u00e9alis\u00e9e tr\u00e8s classiquement par un agent immobilier. Mais si les relations dans la fratrie sont un peu tendues, vous devrez peut-\u00eatre d\u2019abord vous entendre sur la mani\u00e8re d\u2019\u00e9valuer le bien. Dans ce cas, vous pouvez charger des avocats de n\u00e9gocier une convention pr\u00e9voyant la mani\u00e8re dont le prix sera fix\u00e9. En g\u00e9n\u00e9ral, un expert ind\u00e9pendant est d\u00e9sign\u00e9 pour \u00e9valuer le bien. Dans tous les cas, celui qui souhaite conserver le bien doit verser une compensation, appel\u00e9e \u00absoulte\u00bb, aux autres indivisaires. La soulte est proportionnelle \u00e0 la quote-part des droits de chacun dans l\u2019indivision. Elle est due au moment du partage et en un seul versement. Vous pouvez cependant demander des d\u00e9lais de paiement \u00e0 vos fr\u00e8res et s\u0153urs, voire seulement \u00e0 certains d\u2019entre eux. Ils peuvent exiger que les sommes dues portent int\u00e9r\u00eat. Dans ce cas, c\u2019est \u00e0 vous de n\u00e9gocier le taux, mais sachez qu\u2019il est courant de retenir le taux d\u2019int\u00e9r\u00eat l\u00e9gal. Sachez aussi qu\u2019en contrepartie du paiement diff\u00e9r\u00e9, les co\u00efndivisaires peuvent vous demander des garanties (caution solidaire, etc.). \u00bb  Cinq choses \u00e0 savoir sur Patrim, l\u2019outil public d\u2019estimation d\u2019un logement     Si, apr\u00e8s le partage, l\u2019un des co\u00efndivisaires se rend compte qu\u2019il a \u00e9t\u00e9 l\u00e9s\u00e9 dans le calcul de sa part (avec une diff\u00e9rence de valeur de plus d\u2019un quart), il pourra agir en justice pour se faire d\u00e9dommager. Cette action, quand elle est faite dans les deux ans suivant le partage, permet \u00e0 la personne l\u00e9s\u00e9e de demander un compl\u00e9ment, en num\u00e9raire ou en nature.  Et si la fratrie n\u2019arrive pas \u00e0 se mettre d\u2019accord? Si vous ne parvenez pas \u00e0 vous mettre d\u2019accord avec vos fr\u00e8res et s\u0153urs sur le principe du partage ou sur ses modalit\u00e9s, vous pouvez tenter d\u2019obtenir l\u2019attribution du bien indivis, gr\u00e2ce \u00e0 un partage judiciaire. Pour cela, vous devez saisir le tribunal de grande instance (TGI) du lieu d\u2019ouverture de la succession. Vous aurez besoin d\u2019un avocat pour vous assister tout au long de cette proc\u00e9dure complexe. Il vous faudra assigner l\u2019ensemble des co\u00efndivisaires, m\u00eame ceux qui sont d\u2019accord pour vous c\u00e9der leur part. L\u2019assignation doit contenir un descriptif sommaire du  patrimoine  \u00e0 partager, vos intentions en mati\u00e8re de r\u00e9partition des biens et les raisons qui vous ont emp\u00each\u00e9 de parvenir \u00e0 un partage amiable.  Le juge nommera un notaire qui aura un an (renouvelable en cas de complications) pour r\u00e9diger un projet de partage. Si tous les indivisaires approuvent ce projet, le partage est prononc\u00e9. Sinon, le notaire consigne les points d\u2019accord et de d\u00e9saccord dans un proc\u00e8s-verbal. Le juge statuera alors sur les points de d\u00e9saccord et renverra l\u2019affaire devant le notaire afin qu\u2019il rectifie l\u2019acte de partage. En cas de refus de signer persistant, le dernier mot reviendra au magistrat, qui prononcera d\u00e9finitivement le partage."
}